LICENSE
MANIFEST.in
README.rst
setup.py
cerberus/__init__.py
cerberus/admin.py
cerberus/decorators.py
cerberus/models.py
cerberus/settings.py
cerberus/migrations/0001_initial.py
cerberus/migrations/0002_auto_20150708_1401.py
cerberus/migrations/__init__.py
cerberus/templates/cerberus/lockout.html
django_cerberus.egg-info/PKG-INFO
django_cerberus.egg-info/SOURCES.txt
django_cerberus.egg-info/dependency_links.txt
django_cerberus.egg-info/requires.txt
django_cerberus.egg-info/top_level.txt