Metadata-Version: 2.1
Name: django-cerberus
Version: 1.0.1
Summary: Django app that locks out users after too many failed login attempts.
Home-page: https://github.com/PragmaticMates/django-cerberus
Author: Pragmatic Mates
Author-email: info@pragmaticmates.com
Maintainer: Pragmatic Mates
Maintainer-email: info@pragmaticmates.com
License: BSD License
Keywords: django login auth cerberus
Classifier: Programming Language :: Python
Classifier: Programming Language :: Python :: 3.9
Classifier: Operating System :: OS Independent
Classifier: Environment :: Web Environment
Classifier: Intended Audience :: Developers
Classifier: Framework :: Django
Classifier: License :: OSI Approved :: BSD License
Classifier: Development Status :: 3 - Alpha
License-File: LICENSE
Requires-Dist: django>=3
